typespy.py
typespy-0.1.0.dist-info/licenses/LICENSE
typespy-0.1.0.dist-info/METADATA
typespy-0.1.0.dist-info/WHEEL
typespy-0.1.0.dist-info/entry_points.txt
typespy-0.1.0.dist-info/top_level.txt
typespy-0.1.0.dist-info/RECORD
