Metadata-Version: 2.4
Name: typespy
Version: 0.1.0
Summary: Detect python calling types
Author: Rasmus Nygren
Maintainer: Rasmus Nygren
Project-URL: Homepage, https://github.com/rasmusnygren/typespy
Project-URL: Repository, https://github.com/rasmusnygren/typespy
Keywords: type detection,type tracing,typing
Classifier: Programming Language :: Python :: 3.10
Classifier: Programming Language :: Python :: 3.11
Classifier: Programming Language :: Python :: 3.12
Requires-Python: >=3.10
License-File: LICENSE
Dynamic: license-file
